krnel/logging.py
krnel/py.typed
krnel/graph/__init__.py
krnel/graph/classifier_ops.py
krnel/graph/cli.py
krnel/graph/config.py
krnel/graph/dataset_ops.py
krnel/graph/graph_diff.py
krnel/graph/graph_transformations.py
krnel/graph/grouped_ops.py
krnel/graph/llm_ops.py
krnel/graph/op_spec.py
krnel/graph/repr_html.py
krnel/graph/types.py
krnel/graph/viz_ops.py
krnel/graph/runners/__init__.py
krnel/graph/runners/base_runner.py
krnel/graph/runners/cached_runner.py
krnel/graph/runners/model_registry.py
krnel/graph/runners/op_status.py
krnel/graph/runners/local_runner/__init__.py
krnel/graph/runners/local_runner/local_arrow_runner.py
krnel/graph/runners/local_runner/model_registry_implementations.py
krnel/graph/runners/local_runner/probe_implementations.py
krnel_graph-0.1.7.dist-info/licenses/LICENSE
krnel_graph-0.1.7.dist-info/METADATA
krnel_graph-0.1.7.dist-info/WHEEL
krnel_graph-0.1.7.dist-info/entry_points.txt
krnel_graph-0.1.7.dist-info/top_level.txt
krnel_graph-0.1.7.dist-info/RECORD
