Metadata-Version: 2.4
Name: krnel-graph
Version: 0.1.7
Summary: Lightweight dataflow library for mechanistic interpretability.
Author-email: Kimberly Wilber <kimmy+pypispam@krnel.ai>, Peyman Faratin <peyman+pypispam@krnel.ai>
License-Expression: Apache-2.0
Requires-Python: >=3.10
License-File: LICENSE
Requires-Dist: fsspec>=2024.0.0
Requires-Dist: httpx>=0.20
Requires-Dist: numpy>=1.26
Requires-Dist: platformdirs>=4.0
Requires-Dist: pyarrow>=15.0
Requires-Dist: pydantic>=2.11.0
Requires-Dist: pydantic-settings>=2.5.0
Requires-Dist: structlog>=23.0.0
Requires-Dist: tqdm>=4
Requires-Dist: scikit-learn>=1.7.1
Requires-Dist: rich>=13.7
Requires-Dist: cyclopts>=3.22.5
Requires-Dist: humanize>=4.0.0
Provides-Extra: test
Requires-Dist: pytest>=7.0.0; extra == "test"
Requires-Dist: pytest-cov>=4.0.0; extra == "test"
Requires-Dist: ruff>=0.13.1; extra == "test"
Provides-Extra: docs
Requires-Dist: sphinx>=7.1.0; extra == "docs"
Requires-Dist: sphinx-autoapi>=3.0.0; extra == "docs"
Requires-Dist: sphinx-rtd-theme>=2.0.0; extra == "docs"
Requires-Dist: myst-parser>=2.0.0; extra == "docs"
Requires-Dist: sphinx-autobuild>=2024.0.0; extra == "docs"
Requires-Dist: furo>=2025.7.19; extra == "docs"
Requires-Dist: autodoc-pydantic>=2.2.0; extra == "docs"
Requires-Dist: sphinxcontrib-mermaid>=0.9.2; extra == "docs"
Requires-Dist: autoclasstoc>=1.7.0; extra == "docs"
Requires-Dist: sphinx-autodoc-annotation>=1.0.post1; extra == "docs"
Requires-Dist: sphinx-autodoc-typehints>=2.3.0; extra == "docs"
Provides-Extra: ml
Requires-Dist: torch==2.7.0; platform_system == "Darwin" and extra == "ml"
Requires-Dist: torch>=2.5.0; platform_system == "Linux" and extra == "ml"
Requires-Dist: torch>=2.5.0; platform_system == "Windows" and extra == "ml"
Requires-Dist: datasets>=3.0.0; extra == "ml"
Requires-Dist: transformer-lens>=2.15.0; extra == "ml"
Requires-Dist: transformers>=4.55.0; extra == "ml"
Requires-Dist: fsspec[gcs]>=2023.1.0; extra == "ml"
Requires-Dist: sentence-transformers>=5.1.0; extra == "ml"
Provides-Extra: viz
Requires-Dist: numba>=0.61.2; extra == "viz"
Requires-Dist: jupyter-scatter>=0.22.0; extra == "viz"
Requires-Dist: umap-learn>=0.5.8; extra == "viz"
Requires-Dist: seaborn>=0.13.2; extra == "viz"
Requires-Dist: hiplot>=0.1.33; extra == "viz"
Dynamic: license-file
